{
  "type": "object",
  "properties": {
    "id": {
      "type": "integer"
    },
    "postId": {
      "type": "integer"
    },
    "userId": {
      "type": "integer"
    },
    "userName": {
      "type": "string"
    },
    "parentId": {
      "type": "integer"
    },
    "content": {
      "type": "string",
      "maxLength": 1000
    },
    "createdAt": {
      "type": "string",
      "format": "date-time"
    }
  },
  "required": [
    "id",
    "userId",
    "postId",
    "content",
    "createdAt"
  ],
  "additionalProperties": false
}
